cloverwallpaper/__init__.py
cloverwallpaper/__main__.py
cloverwallpaper/cloverwallpaper.py
cloverwallpaper-0.6.7.dist-info/LICENSE
cloverwallpaper-0.6.7.dist-info/METADATA
cloverwallpaper-0.6.7.dist-info/WHEEL
cloverwallpaper-0.6.7.dist-info/entry_points.txt
cloverwallpaper-0.6.7.dist-info/top_level.txt
cloverwallpaper-0.6.7.dist-info/RECORD
