Metadata-Version: 2.1
Name: cloverwallpaper
Version: 0.6.7
Summary: A tool to download wallpapers from 4chan.
Home-page: https://github.com/collinarnett/clover_wallpaper
Author: Collin Arnett
Author-email: collin@arnett.it
License: GPLv3
Keywords: 4chan,wallpaper,downloader,image,scraper
Platform: UNKNOWN
Classifier: Development Status :: 3 - Alpha
Classifier: Operating System :: POSIX :: Linux
Classifier: Operating System :: Microsoft :: Windows
Classifier: Intended Audience :: End Users/Desktop
Classifier: Topic :: Utilities
Classifier: License :: OSI Approved :: GNU General Public License v3 (GPLv3)
Classifier: Programming Language :: Python :: 3
Requires-Python: >=3.6
License-File: LICENSE
Requires-Dist: requests
Requires-Dist: tqdm
